scrapyslackbot/__init__.py
scrapyslackbot/extensions.py
scrapy_slackbot-0.3.0.dist-info/WHEEL
scrapy_slackbot-0.3.0.dist-info/METADATA
scrapy_slackbot-0.3.0.dist-info/license_files/LICENSE
scrapy_slackbot-0.3.0.dist-info/RECORD
