Metadata-Version: 2.1
Name: scrapy-slackbot
Version: 0.3.0
Summary: A Scrapy extension to send notification to the Slack channel.
License: MIT
Keywords: scrapy,slack,slackbot
Author-email: Yuchen Cheng <rudeigerc@gmail.com>
Requires-Python: >=3.9
Requires-Dist: Scrapy>=2.6.2
Requires-Dist: slack-sdk>=3.18.1
Project-URL: Homepage, https://github.com/rudeigerc/scrapy-slackbot
Project-URL: Repository, https://github.com/rudeigerc/scrapy-slackbot
